make_gtfs/__init__.py
make_gtfs/cli.py
make_gtfs/constants.py
make_gtfs/hashables.py
make_gtfs/main.py
make_gtfs/protofeed.py
make_gtfs/validators.py
make_gtfs-4.1.1.dist-info/METADATA
make_gtfs-4.1.1.dist-info/WHEEL
make_gtfs-4.1.1.dist-info/entry_points.txt
make_gtfs-4.1.1.dist-info/licenses/LICENSE.txt
make_gtfs-4.1.1.dist-info/RECORD
