Metadata-Version: 2.4
Name: make-gtfs
Version: 4.1.1
Summary: A Python 3.10+ library to build GTFS feeds from basic route information.
Author-email: Alexander Raichev <araichev@mrcagney.com>
License-Expression: MIT
License-File: LICENSE.txt
Requires-Python: >=3.10
Requires-Dist: click>=8.1.7
Requires-Dist: gtfs-kit>=8
Requires-Dist: pandera>=0.11.0
